Metadata-Version: 2.1
Name: ipython-mermaid-magic
Version: 0.3
Summary: Cell magic to allow for usage of mermaid notation inside Databricks
Home-page: https://github.com/sgmarius/ipython-mermaid
Author: Marius Sandu
Author-email: marius@ltng-bi.com
License: MIT
Download-URL: https://github.com/sgmarius/ipython-mermaid/blob/main/dist/ipython-mermaid-magic-0.3.tar.gz
Keywords: IPython,Mermaid
Platform: UNKNOWN
Classifier: Development Status :: 3 - Alpha
Classifier: Intended Audience :: Developers
Classifier: Topic :: Software Development :: Build Tools
Classifier: License :: OSI Approved :: MIT License
Classifier: Programming Language :: Python :: 3
Classifier: Programming Language :: Python :: 3.4
Classifier: Programming Language :: Python :: 3.5
Classifier: Programming Language :: Python :: 3.6
License-File: LICENSE.txt
